{"months": [{"id": "1", "days": [{"tempAvg": "64.3", "colour": "3", "humidity": "0.731", "chanceClear": "0.5247", "perfectFactor": "4.8967021996", "chanceRain": "0.171"}, {"tempAvg": "64.3", "colour": "3", "humidity": "0.729", "chanceClear": "0.5337", "perfectFactor": "4.9610749558", "chanceRain": "0.172"}, {"tempAvg": "64.2", "colour": "3", "humidity": "0.7309", "chanceClear": "0.5341", "perfectFactor": "5.042378879", "chanceRain": "0.172"}, {"tempAvg": "64.1", "colour": "3", "humidity": "0.7296", "chanceClear": "0.5358", "perfectFactor": "5.1079910907", "chanceRain": "0.173"}, {"tempAvg": "64.1", "colour": "3", "humidity": "0.7259", "chanceClear": "0.5434", "perfectFactor": "5.1541734204", "chanceRain": "0.173"}, {"tempAvg": "64", "colour": "3", "humidity": "0.7226", "chanceClear": "0.5508", "perfectFactor": "5.2664429146", "chanceRain": "0.173"}, {"tempAvg": "64", "colour": "3", "humidity": "0.7185", "chanceClear": "0.5527", "perfectFactor": "5.2546250184", "chanceRain": "0.173"}, {"tempAvg": "63.9", "colour": "3", "humidity": "0.7149", "chanceClear": "0.5624", "perfectFactor": "5.3865554286", "chanceRain": "0.173"}, {"tempAvg": "63.9", "colour": "3", "humidity": "0.7102", "chanceClear": "0.5689", "perfectFactor": "5.4129887668", "chanceRain": "0.173"}, {"tempAvg": "63.9", "colour": "3", "humidity": "0.7068", "chanceClear": "0.5741", "perfectFactor": "5.4363149799", "chanceRain": "0.173"}, {"tempAvg": "63.9", "colour": "3", "humidity": "0.7056", "chanceClear": "0.5846", "perfectFactor": "5.5263439002", "chanceRain": "0.173"}, {"tempAvg": "63.9", "colour": "3", "humidity": "0.7059", "chanceClear": "0.5882", "perfectFactor": "5.562739545", "chanceRain": "0.173"}, {"tempAvg": "63.9", "colour": "3", "humidity": "0.7074", "chanceClear": "0.5851", "perfectFactor": "5.5451803767", "chanceRain": "0.173"}, {"tempAvg": "63.9", "colour": "3", "humidity": "0.7074", "chanceClear": "0.5805", "perfectFactor": "5.4949322408", "chanceRain": "0.174"}, {"tempAvg": "63.9", "colour": "3", "humidity": "0.7066", "chanceClear": "0.5793", "perfectFactor": "5.4773718245", "chanceRain": "0.174"}, {"tempAvg": "64", "colour": "3", "humidity": "0.7048", "chanceClear": "0.5811", "perfectFactor": "5.406182496", "chanceRain": "0.175"}, {"tempAvg": "64", "colour": "3", "humidity": "0.7035", "chanceClear": "0.5805", "perfectFactor": "5.3906391", "chanceRain": "0.175"}, {"tempAvg": "64", "colour": "3", "humidity": "0.7006", "chanceClear": "0.5816", "perfectFactor": "5.3720707686", "chanceRain": "0.176"}, {"tempAvg": "64.1", "colour": "3", "humidity": "0.698", "chanceClear": "0.5838", "perfectFactor": "5.3052250541", "chanceRain": "0.176"}, {"tempAvg": "64.2", "colour": "3", "humidity": "0.6973", "chanceClear": "0.5819", "perfectFactor": "5.2157868185", "chanceRain": "0.176"}, {"tempAvg": "64.2", "colour": "3", "humidity": "0.6982", "chanceClear": "0.5831", "perfectFactor": "5.2332887268", "chanceRain": "0.176"}, {"tempAvg": "64.3", "colour": "3", "humidity": "0.6999", "chanceClear": "0.5896", "perfectFactor": "5.2365035332", "chanceRain": "0.176"}, {"tempAvg": "64.3", "colour": "3", "humidity": "0.7035", "chanceClear": "0.5889", "perfectFactor": "5.257188977", "chanceRain": "0.176"}, {"tempAvg": "64.4", "colour": "3", "humidity": "0.7037", "chanceClear": "0.586", "perfectFactor": "5.171097228", "chanceRain": "0.175"}, {"tempAvg": "64.5", "colour": "3", "humidity": "0.706", "chanceClear": "0.5824", "perfectFactor": "5.0882832", "chanceRain": "0.175"}, {"tempAvg": "64.5", "colour": "3", "humidity": "0.7068", "chanceClear": "0.5732", "perfectFactor": "5.01357978", "chanceRain": "0.175"}, {"tempAvg": "64.6", "colour": "3", "humidity": "0.7056", "chanceClear": "0.5689", "perfectFactor": "4.9072283608", "chanceRain": "0.174"}, {"tempAvg": "64.7", "colour": "3", "humidity": "0.7025", "chanceClear": "0.5702", "perfectFactor": "4.8306597038", "chanceRain": "0.174"}, {"tempAvg": "64.8", "colour": "3", "humidity": "0.699", "chanceClear": "0.5752", "perfectFactor": "4.7881092902", "chanceRain": "0.173"}, {"tempAvg": "64.9", "colour": "3", "humidity": "0.6983", "chanceClear": "0.5777", "perfectFactor": "4.7373804503", "chanceRain": "0.173"}, {"tempAvg": "65", "colour": "3", "humidity": "0.6982", "chanceClear": "0.5733", "perfectFactor": "4.6344193787", "chanceRain": "0.173"}]}, {"id": "2", "days": [{"tempAvg": "65.1", "colour": "3", "humidity": "0.6979", "chanceClear": "0.5712", "perfectFactor": "4.5440231034", "chanceRain": "0.174"}, {"tempAvg": "65.2", "colour": "3", "humidity": "0.6969", "chanceClear": "0.5758", "perfectFactor": "4.5077630647", "chanceRain": "0.174"}, {"tempAvg": "65.3", "colour": "3", "humidity": "0.6987", "chanceClear": "0.5803", "perfectFactor": "4.4877448737", "chanceRain": "0.174"}, {"tempAvg": "65.5", "colour": "3", "humidity": "0.6996", "chanceClear": "0.578", "perfectFactor": "4.33685538", "chanceRain": "0.175"}, {"tempAvg": "65.6", "colour": "3", "humidity": "0.6998", "chanceClear": "0.569", "perfectFactor": "4.204846272", "chanceRain": "0.175"}, {"tempAvg": "65.7", "colour": "3", "humidity": "0.6984", "chanceClear": "0.5641", "perfectFactor": "4.0952915388", "chanceRain": "0.175"}, {"tempAvg": "65.8", "colour": "3", "humidity": "0.6928", "chanceClear": "0.564", "perfectFactor": "3.9924168499", "chanceRain": "0.176"}, {"tempAvg": "65.9", "colour": "3", "humidity": "0.6926", "chanceClear": "0.5676", "perfectFactor": "3.9519543233", "chanceRain": "0.176"}, {"tempAvg": "66", "colour": "3", "humidity": "0.6905", "chanceClear": "0.567", "perfectFactor": "3.871285488", "chanceRain": "0.176"}, {"tempAvg": "66.1", "colour": "3", "humidity": "0.6875", "chanceClear": "0.5781", "perfectFactor": "3.8597352338", "chanceRain": "0.177"}, {"tempAvg": "66.2", "colour": "4", "humidity": "0.6882", "chanceClear": "0.5839", "perfectFactor": "3.8362859211", "chanceRain": "0.177"}, {"tempAvg": "66.3", "colour": "4", "humidity": "0.6876", "chanceClear": "0.5872", "perfectFactor": "3.7881450628", "chanceRain": "0.177"}, {"tempAvg": "66.4", "colour": "4", "humidity": "0.6899", "chanceClear": "0.5822", "perfectFactor": "3.7023391881", "chanceRain": "0.177"}, {"tempAvg": "66.5", "colour": "4", "humidity": "0.6906", "chanceClear": "0.5829", "perfectFactor": "3.6442918492", "chanceRain": "0.177"}, {"tempAvg": "66.6", "colour": "4", "humidity": "0.6905", "chanceClear": "0.5863", "perfectFactor": "3.5983811893", "chanceRain": "0.177"}, {"tempAvg": "66.7", "colour": "4", "humidity": "0.6921", "chanceClear": "0.5825", "perfectFactor": "3.5212580748", "chanceRain": "0.176"}, {"tempAvg": "66.9", "colour": "4", "humidity": "0.6932", "chanceClear": "0.5775", "perfectFactor": "3.3605514558", "chanceRain": "0.177"}, {"tempAvg": "67", "colour": "4", "humidity": "0.6923", "chanceClear": "0.5691", "perfectFactor": "3.2425206639", "chanceRain": "0.177"}, {"tempAvg": "67.1", "colour": "4", "humidity": "0.6912", "chanceClear": "0.5686", "perfectFactor": "3.1698338273", "chanceRain": "0.177"}, {"tempAvg": "67.2", "colour": "4", "humidity": "0.6916", "chanceClear": "0.5689", "perfectFactor": "3.1048024251", "chanceRain": "0.178"}, {"tempAvg": "67.3", "colour": "4", "humidity": "0.6914", "chanceClear": "0.5698", "perfectFactor": "3.0403447431", "chanceRain": "0.179"}, {"tempAvg": "67.4", "colour": "4", "humidity": "0.6938", "chanceClear": "0.5673", "perfectFactor": "2.9728846838", "chanceRain": "0.179"}, {"tempAvg": "67.5", "colour": "4", "humidity": "0.693", "chanceClear": "0.5673", "perfectFactor": "2.901365082", "chanceRain": "0.18"}, {"tempAvg": "67.6", "colour": "4", "humidity": "0.6926", "chanceClear": "0.5663", "perfectFactor": "2.8268035155", "chanceRain": "0.181"}, {"tempAvg": "67.7", "colour": "4", "humidity": "0.6891", "chanceClear": "0.5623", "perfectFactor": "2.7258508464", "chanceRain": "0.182"}, {"tempAvg": "67.8", "colour": "4", "humidity": "0.6851", "chanceClear": "0.5667", "perfectFactor": "2.6644558155", "chanceRain": "0.183"}, {"tempAvg": "67.9", "colour": "4", "humidity": "0.6836", "chanceClear": "0.5669", "perfectFactor": "2.593059739", "chanceRain": "0.184"}, {"tempAvg": "68", "colour": "4", "humidity": "0.6836", "chanceClear": "0.5698", "perfectFactor": "2.5396396256", "chanceRain": "0.185"}, {"tempAvg": "68.1", "colour": "4", "humidity": "0.6836", "chanceClear": "0.5698", "perfectFactor": "2.476148635", "chanceRain": "0.185"}]}, {"id": "3", "days": [{"tempAvg": "68.2", "colour": "4", "humidity": "0.6787", "chanceClear": "0.5683", "perfectFactor": "2.3861267111", "chanceRain": "0.186"}, {"tempAvg": "68.3", "colour": "4", "humidity": "0.6745", "chanceClear": "0.5677", "perfectFactor": "2.3036851011", "chanceRain": "0.187"}, {"tempAvg": "68.4", "colour": "4", "humidity": "0.6711", "chanceClear": "0.5738", "perfectFactor": "2.2513152252", "chanceRain": "0.188"}, {"tempAvg": "68.5", "colour": "4", "humidity": "0.6694", "chanceClear": "0.5745", "perfectFactor": "2.1858975852", "chanceRain": "0.188"}, {"tempAvg": "68.6", "colour": "4", "humidity": "0.6689", "chanceClear": "0.5758", "perfectFactor": "2.1240396688", "chanceRain": "0.189"}, {"tempAvg": "68.8", "colour": "4", "humidity": "0.6695", "chanceClear": "0.5769", "perfectFactor": "2.0022399072", "chanceRain": "0.19"}, {"tempAvg": "68.9", "colour": "4", "humidity": "0.6701", "chanceClear": "0.5787", "perfectFactor": "1.9474656611", "chanceRain": "0.19"}, {"tempAvg": "69", "colour": "4", "humidity": "0.6695", "chanceClear": "0.5782", "perfectFactor": "1.881329814", "chanceRain": "0.19"}, {"tempAvg": "69.1", "colour": "5", "humidity": "0.6703", "chanceClear": "0.5766", "perfectFactor": "1.8135117452", "chanceRain": "0.191"}, {"tempAvg": "69.2", "colour": "5", "humidity": "0.6704", "chanceClear": "0.5737", "perfectFactor": "1.7424302578", "chanceRain": "0.191"}, {"tempAvg": "69.3", "colour": "5", "humidity": "0.6696", "chanceClear": "0.5715", "perfectFactor": "1.671760121", "chanceRain": "0.191"}, {"tempAvg": "69.4", "colour": "5", "humidity": "0.6721", "chanceClear": "0.57", "perfectFactor": "1.6096203552", "chanceRain": "0.192"}, {"tempAvg": "69.5", "colour": "5", "humidity": "0.674", "chanceClear": "0.5688", "perfectFactor": "1.546902792", "chanceRain": "0.193"}, {"tempAvg": "69.7", "colour": "5", "humidity": "0.6737", "chanceClear": "0.575", "perfectFactor": "1.4380227555", "chanceRain": "0.193"}, {"tempAvg": "69.8", "colour": "5", "humidity": "0.6724", "chanceClear": "0.5741", "perfectFactor": "1.3706970019", "chanceRain": "0.193"}, {"tempAvg": "69.9", "colour": "5", "humidity": "0.6751", "chanceClear": "0.5715", "perfectFactor": "1.3060766792", "chanceRain": "0.194"}, {"tempAvg": "70", "colour": "5", "humidity": "0.6773", "chanceClear": "0.5729", "perfectFactor": "1.2509931481", "chanceRain": "0.194"}, {"tempAvg": "70.2", "colour": "5", "humidity": "0.6781", "chanceClear": "0.5757", "perfectFactor": "1.1341382803", "chanceRain": "0.193"}, {"tempAvg": "70.3", "colour": "5", "humidity": "0.6802", "chanceClear": "0.5771", "perfectFactor": "1.0770606358", "chanceRain": "0.193"}, {"tempAvg": "70.4", "colour": "5", "humidity": "0.6806", "chanceClear": "0.5773", "perfectFactor": "1.0159090785", "chanceRain": "0.192"}, {"tempAvg": "70.5", "colour": "5", "humidity": "0.6807", "chanceClear": "0.574", "perfectFactor": "0.9482818086", "chanceRain": "0.191"}, {"tempAvg": "70.7", "colour": "5", "humidity": "0.68", "chanceClear": "0.5717", "perfectFactor": "0.818720136", "chanceRain": "0.19"}, {"tempAvg": "70.8", "colour": "5", "humidity": "0.6813", "chanceClear": "0.5688", "perfectFactor": "0.7552056799", "chanceRain": "0.188"}, {"tempAvg": "70.9", "colour": "5", "humidity": "0.6796", "chanceClear": "0.5726", "perfectFactor": "0.6960139439", "chanceRain": "0.187"}, {"tempAvg": "71", "colour": "5", "humidity": "0.677", "chanceClear": "0.5836", "perfectFactor": "0.644008436", "chanceRain": "0.185"}, {"tempAvg": "71.1", "colour": "5", "humidity": "0.6743", "chanceClear": "0.5956", "perfectFactor": "0.5906121954", "chanceRain": "0.183"}, {"tempAvg": "71.2", "colour": "5", "humidity": "0.6702", "chanceClear": "0.6036", "perfectFactor": "0.5300996763", "chanceRain": "0.181"}, {"tempAvg": "71.4", "colour": "5", "humidity": "0.6701", "chanceClear": "0.6042", "perfectFactor": "0.3988822786", "chanceRain": "0.179"}, {"tempAvg": "71.5", "colour": "5", "humidity": "0.6682", "chanceClear": "0.6081", "perfectFactor": "0.3344115817", "chanceRain": "0.177"}, {"tempAvg": "71.6", "colour": "5", "humidity": "0.6673", "chanceClear": "0.6175", "perfectFactor": "0.271958115", "chanceRain": "0.175"}, {"tempAvg": "71.7", "colour": "5", "humidity": "0.6649", "chanceClear": "0.6211", "perfectFactor": "0.2049154113", "chanceRain": "0.173"}]}, {"id": "4", "days": [{"tempAvg": "71.9", "colour": "5", "humidity": "0.6657", "chanceClear": "0.62", "perfectFactor": "0.0684312972", "chanceRain": "0.171"}, {"tempAvg": "72", "colour": "5", "humidity": "0.6674", "chanceClear": "0.6113", "perfectFactor": "0", "chanceRain": "0.168"}, {"tempAvg": "72.1", "colour": "5", "humidity": "0.665", "chanceClear": "0.6121", "perfectFactor": "0.0678139469", "chanceRain": "0.167"}, {"tempAvg": "72.2", "colour": "5", "humidity": "0.6637", "chanceClear": "0.6059", "perfectFactor": "0.1343133672", "chanceRain": "0.165"}, {"tempAvg": "72.4", "colour": "5", "humidity": "0.6626", "chanceClear": "0.606", "perfectFactor": "0.2688682378", "chanceRain": "0.163"}, {"tempAvg": "72.5", "colour": "5", "humidity": "0.6612", "chanceClear": "0.6139", "perfectFactor": "0.3401531498", "chanceRain": "0.162"}, {"tempAvg": "72.6", "colour": "5", "humidity": "0.659", "chanceClear": "0.6155", "perfectFactor": "0.408859416", "chanceRain": "0.16"}, {"tempAvg": "72.8", "colour": "5", "humidity": "0.6592", "chanceClear": "0.6123", "perfectFactor": "0.5431220521", "chanceRain": "0.159"}, {"tempAvg": "72.9", "colour": "5", "humidity": "0.6576", "chanceClear": "0.607", "perfectFactor": "0.6049717459", "chanceRain": "0.158"}, {"tempAvg": "73", "colour": "5", "humidity": "0.6569", "chanceClear": "0.6005", "perfectFactor": "0.6658627436", "chanceRain": "0.156"}, {"tempAvg": "73.1", "colour": "5", "humidity": "0.6547", "chanceClear": "0.6018", "perfectFactor": "0.7324431371", "chanceRain": "0.155"}, {"tempAvg": "73.3", "colour": "5", "humidity": "0.6534", "chanceClear": "0.6019", "perfectFactor": "0.8660844312", "chanceRain": "0.153"}, {"tempAvg": "73.5", "colour": "5", "humidity": "0.6535", "chanceClear": "0.5974", "perfectFactor": "0.9931798896", "chanceRain": "0.152"}, {"tempAvg": "73.6", "colour": "5", "humidity": "0.6542", "chanceClear": "0.5935", "perfectFactor": "1.0548456874", "chanceRain": "0.151"}, {"tempAvg": "73.7", "colour": "5", "humidity": "0.6541", "chanceClear": "0.6038", "perfectFactor": "1.1427355412", "chanceRain": "0.149"}, {"tempAvg": "73.9", "colour": "5", "humidity": "0.6522", "chanceClear": "0.6082", "perfectFactor": "1.2842524463", "chanceRain": "0.148"}, {"tempAvg": "74", "colour": "5", "humidity": "0.65", "chanceClear": "0.6167", "perfectFactor": "1.36611384", "chanceRain": "0.148"}, {"tempAvg": "74.2", "colour": "5", "humidity": "0.6501", "chanceClear": "0.6174", "perfectFactor": "1.5064284146", "chanceRain": "0.147"}, {"tempAvg": "74.3", "colour": "5", "humidity": "0.6512", "chanceClear": "0.6185", "perfectFactor": "1.5785252102", "chanceRain": "0.148"}, {"tempAvg": "74.5", "colour": "5", "humidity": "0.6507", "chanceClear": "0.6272", "perfectFactor": "1.7385871104", "chanceRain": "0.148"}, {"tempAvg": "74.6", "colour": "5", "humidity": "0.6487", "chanceClear": "0.631", "perfectFactor": "1.8134943029", "chanceRain": "0.148"}, {"tempAvg": "74.8", "colour": "4", "humidity": "0.6476", "chanceClear": "0.6356", "perfectFactor": "1.9615903471", "chanceRain": "0.149"}, {"tempAvg": "75", "colour": "4", "humidity": "0.6458", "chanceClear": "0.6389", "perfectFactor": "2.104268262", "chanceRain": "0.15"}, {"tempAvg": "75.1", "colour": "4", "humidity": "0.6484", "chanceClear": "0.6369", "perfectFactor": "2.1712098313", "chanceRain": "0.152"}, {"tempAvg": "75.3", "colour": "4", "humidity": "0.6502", "chanceClear": "0.6388", "perfectFactor": "2.3191357527", "chanceRain": "0.154"}, {"tempAvg": "75.4", "colour": "4", "humidity": "0.6542", "chanceClear": "0.6313", "perfectFactor": "2.3702692832", "chanceRain": "0.156"}, {"tempAvg": "75.6", "colour": "4", "humidity": "0.6556", "chanceClear": "0.6321", "perfectFactor": "2.5152711313", "chanceRain": "0.157"}, {"tempAvg": "75.8", "colour": "4", "humidity": "0.6573", "chanceClear": "0.6333", "perfectFactor": "2.6574554866", "chanceRain": "0.16"}, {"tempAvg": "76", "colour": "4", "humidity": "0.6553", "chanceClear": "0.6391", "perfectFactor": "2.8076501499", "chanceRain": "0.162"}, {"tempAvg": "76.2", "colour": "4", "humidity": "0.6535", "chanceClear": "0.6338", "perfectFactor": "2.9051167362", "chanceRain": "0.165"}]}, {"id": "5", "days": [{"tempAvg": "76.4", "colour": "4", "humidity": "0.6529", "chanceClear": "0.6302", "perfectFactor": "3.0125278177", "chanceRain": "0.168"}, {"tempAvg": "76.5", "colour": "4", "humidity": "0.6526", "chanceClear": "0.6334", "perfectFactor": "3.0877755948", "chanceRain": "0.17"}, {"tempAvg": "76.7", "colour": "4", "humidity": "0.6533", "chanceClear": "0.6352", "perfectFactor": "3.2259416726", "chanceRain": "0.173"}, {"tempAvg": "76.9", "colour": "4", "humidity": "0.6515", "chanceClear": "0.6429", "perfectFactor": "3.3822922711", "chanceRain": "0.176"}, {"tempAvg": "77.1", "colour": "4", "humidity": "0.6495", "chanceClear": "0.6416", "perfectFactor": "3.4896899246", "chanceRain": "0.179"}, {"tempAvg": "77.3", "colour": "4", "humidity": "0.6509", "chanceClear": "0.6373", "perfectFactor": "3.5924117799", "chanceRain": "0.183"}, {"tempAvg": "77.5", "colour": "4", "humidity": "0.6525", "chanceClear": "0.6347", "perfectFactor": "3.7082252295", "chanceRain": "0.186"}, {"tempAvg": "77.6", "colour": "4", "humidity": "0.6535", "chanceClear": "0.6392", "perfectFactor": "3.7895304384", "chanceRain": "0.19"}, {"tempAvg": "77.8", "colour": "3", "humidity": "0.6547", "chanceClear": "0.6402", "perfectFactor": "3.9139194217", "chanceRain": "0.195"}, {"tempAvg": "78", "colour": "3", "humidity": "0.6559", "chanceClear": "0.6355", "perfectFactor": "4.0065166134", "chanceRain": "0.199"}, {"tempAvg": "78.2", "colour": "3", "humidity": "0.6547", "chanceClear": "0.6388", "perfectFactor": "4.1228360249", "chanceRain": "0.205"}, {"tempAvg": "78.4", "colour": "3", "humidity": "0.6554", "chanceClear": "0.6289", "perfectFactor": "4.1626989612", "chanceRain": "0.211"}, {"tempAvg": "78.6", "colour": "3", "humidity": "0.6553", "chanceClear": "0.6195", "perfectFactor": "4.1958231223", "chanceRain": "0.217"}, {"tempAvg": "78.8", "colour": "3", "humidity": "0.6573", "chanceClear": "0.6129", "perfectFactor": "4.2516145365", "chanceRain": "0.224"}, {"tempAvg": "79", "colour": "3", "humidity": "0.6599", "chanceClear": "0.6128", "perfectFactor": "4.3592888416", "chanceRain": "0.23"}, {"tempAvg": "79.2", "colour": "3", "humidity": "0.6624", "chanceClear": "0.6097", "perfectFactor": "4.4373486044", "chanceRain": "0.237"}, {"tempAvg": "79.4", "colour": "3", "humidity": "0.6625", "chanceClear": "0.6036", "perfectFactor": "4.474233288", "chanceRain": "0.244"}, {"tempAvg": "79.5", "colour": "3", "humidity": "0.6636", "chanceClear": "0.5981", "perfectFactor": "4.46511555", "chanceRain": "0.25"}, {"tempAvg": "79.7", "colour": "3", "humidity": "0.667", "chanceClear": "0.5904", "perfectFactor": "4.505901745", "chanceRain": "0.257"}, {"tempAvg": "79.9", "colour": "3", "humidity": "0.6709", "chanceClear": "0.583", "perfectFactor": "4.5422472711", "chanceRain": "0.265"}, {"tempAvg": "80.1", "colour": "3", "humidity": "0.6739", "chanceClear": "0.576", "perfectFactor": "4.577879255", "chanceRain": "0.272"}, {"tempAvg": "80.2", "colour": "3", "humidity": "0.6742", "chanceClear": "0.5729", "perfectFactor": "4.5608303174", "chanceRain": "0.28"}, {"tempAvg": "80.4", "colour": "3", "humidity": "0.6768", "chanceClear": "0.567", "perfectFactor": "4.590211369", "chanceRain": "0.288"}, {"tempAvg": "80.5", "colour": "3", "humidity": "0.6767", "chanceClear": "0.5634", "perfectFactor": "4.562833271", "chanceRain": "0.296"}, {"tempAvg": "80.7", "colour": "3", "humidity": "0.6798", "chanceClear": "0.5616", "perfectFactor": "4.6234561951", "chanceRain": "0.304"}, {"tempAvg": "80.8", "colour": "3", "humidity": "0.6839", "chanceClear": "0.5565", "perfectFactor": "4.6017940399", "chanceRain": "0.313"}, {"tempAvg": "81", "colour": "3", "humidity": "0.6861", "chanceClear": "0.559", "perfectFactor": "4.6736953614", "chanceRain": "0.323"}, {"tempAvg": "81.1", "colour": "3", "humidity": "0.689", "chanceClear": "0.5621", "perfectFactor": "4.7084792154", "chanceRain": "0.332"}, {"tempAvg": "81.2", "colour": "3", "humidity": "0.6914", "chanceClear": "0.5617", "perfectFactor": "4.7019446855", "chanceRain": "0.342"}, {"tempAvg": "81.4", "colour": "3", "humidity": "0.6946", "chanceClear": "0.5558", "perfectFactor": "4.7031212632", "chanceRain": "0.352"}, {"tempAvg": "81.5", "colour": "3", "humidity": "0.6972", "chanceClear": "0.5557", "perfectFactor": "4.6964754329", "chanceRain": "0.362"}]}, {"id": "6", "days": [{"tempAvg": "81.6", "colour": "3", "humidity": "0.7033", "chanceClear": "0.5514", "perfectFactor": "4.6684869454", "chanceRain": "0.373"}, {"tempAvg": "81.7", "colour": "3", "humidity": "0.7078", "chanceClear": "0.55", "perfectFactor": "4.659723442", "chanceRain": "0.383"}, {"tempAvg": "81.8", "colour": "3", "humidity": "0.7087", "chanceClear": "0.5472", "perfectFactor": "4.6061408817", "chanceRain": "0.394"}, {"tempAvg": "81.9", "colour": "3", "humidity": "0.7112", "chanceClear": "0.5458", "perfectFactor": "4.5807514664", "chanceRain": "0.404"}, {"tempAvg": "82", "colour": "3", "humidity": "0.7135", "chanceClear": "0.5421", "perfectFactor": "4.533159462", "chanceRain": "0.414"}, {"tempAvg": "82.1", "colour": "3", "humidity": "0.7167", "chanceClear": "0.5395", "perfectFactor": "4.4988623597", "chanceRain": "0.424"}, {"tempAvg": "82.2", "colour": "3", "humidity": "0.7182", "chanceClear": "0.5387", "perfectFactor": "4.4672368074", "chanceRain": "0.434"}, {"tempAvg": "82.2", "colour": "3", "humidity": "0.7211", "chanceClear": "0.54", "perfectFactor": "4.4246061432", "chanceRain": "0.443"}, {"tempAvg": "82.3", "colour": "3", "humidity": "0.7227", "chanceClear": "0.5414", "perfectFactor": "4.4169662925", "chanceRain": "0.452"}, {"tempAvg": "82.4", "colour": "3", "humidity": "0.7246", "chanceClear": "0.5341", "perfectFactor": "4.3388337312", "chanceRain": "0.461"}, {"tempAvg": "82.4", "colour": "3", "humidity": "0.7265", "chanceClear": "0.528", "perfectFactor": "4.2366969216", "chanceRain": "0.469"}, {"tempAvg": "82.5", "colour": "3", "humidity": "0.7287", "chanceClear": "0.5239", "perfectFactor": "4.1929352092", "chanceRain": "0.477"}, {"tempAvg": "82.5", "colour": "3", "humidity": "0.7338", "chanceClear": "0.5165", "perfectFactor": "4.0910091138", "chanceRain": "0.486"}, {"tempAvg": "82.6", "colour": "3", "humidity": "0.7372", "chanceClear": "0.5122", "perfectFactor": "4.0505246404", "chanceRain": "0.494"}, {"tempAvg": "82.7", "colour": "3", "humidity": "0.7395", "chanceClear": "0.5065", "perfectFactor": "3.9917261961", "chanceRain": "0.502"}, {"tempAvg": "82.7", "colour": "3", "humidity": "0.7404", "chanceClear": "0.5027", "perfectFactor": "3.9028795529", "chanceRain": "0.51"}, {"tempAvg": "82.7", "colour": "4", "humidity": "0.7431", "chanceClear": "0.4953", "perfectFactor": "3.796438779", "chanceRain": "0.518"}, {"tempAvg": "82.8", "colour": "4", "humidity": "0.7467", "chanceClear": "0.4887", "perfectFactor": "3.7440000954", "chanceRain": "0.525"}, {"tempAvg": "82.8", "colour": "4", "humidity": "0.7488", "chanceClear": "0.4862", "perfectFactor": "3.6881398794", "chanceRain": "0.531"}, {"tempAvg": "82.8", "colour": "4", "humidity": "0.7536", "chanceClear": "0.4864", "perfectFactor": "3.6658036408", "chanceRain": "0.537"}, {"tempAvg": "82.8", "colour": "4", "humidity": "0.7552", "chanceClear": "0.4844", "perfectFactor": "3.6189730161", "chanceRain": "0.542"}, {"tempAvg": "82.8", "colour": "4", "humidity": "0.7595", "chanceClear": "0.4826", "perfectFactor": "3.5864687326", "chanceRain": "0.547"}, {"tempAvg": "82.9", "colour": "4", "humidity": "0.7612", "chanceClear": "0.4818", "perfectFactor": "3.581789697", "chanceRain": "0.552"}, {"tempAvg": "82.9", "colour": "4", "humidity": "0.7634", "chanceClear": "0.4781", "perfectFactor": "3.532729322", "chanceRain": "0.556"}, {"tempAvg": "82.9", "colour": "4", "humidity": "0.7654", "chanceClear": "0.478", "perfectFactor": "3.5173164046", "chanceRain": "0.559"}, {"tempAvg": "82.9", "colour": "4", "humidity": "0.7651", "chanceClear": "0.4807", "perfectFactor": "3.5197623216", "chanceRain": "0.561"}, {"tempAvg": "82.9", "colour": "4", "humidity": "0.7651", "chanceClear": "0.4776", "perfectFactor": "3.4731656964", "chanceRain": "0.564"}, {"tempAvg": "82.9", "colour": "4", "humidity": "0.7634", "chanceClear": "0.4818", "perfectFactor": "3.4798872625", "chanceRain": "0.566"}, {"tempAvg": "82.9", "colour": "4", "humidity": "0.7628", "chanceClear": "0.4839", "perfectFactor": "3.4842611334", "chanceRain": "0.567"}, {"tempAvg": "82.9", "colour": "4", "humidity": "0.7628", "chanceClear": "0.4907", "perfectFactor": "3.5250638089", "chanceRain": "0.568"}]}, {"id": "7", "days": [{"tempAvg": "83", "colour": "4", "humidity": "0.7613", "chanceClear": "0.4993", "perfectFactor": "3.6042702474", "chanceRain": "0.569"}, {"tempAvg": "83", "colour": "4", "humidity": "0.759", "chanceClear": "0.5058", "perfectFactor": "3.631714812", "chanceRain": "0.57"}, {"tempAvg": "83", "colour": "4", "humidity": "0.7579", "chanceClear": "0.5099", "perfectFactor": "3.647345396", "chanceRain": "0.571"}, {"tempAvg": "83", "colour": "4", "humidity": "0.7569", "chanceClear": "0.5142", "perfectFactor": "3.6646881797", "chanceRain": "0.572"}, {"tempAvg": "83", "colour": "4", "humidity": "0.7557", "chanceClear": "0.5152", "perfectFactor": "3.6659938022", "chanceRain": "0.572"}, {"tempAvg": "83", "colour": "4", "humidity": "0.7564", "chanceClear": "0.5127", "perfectFactor": "3.6515839325", "chanceRain": "0.572"}, {"tempAvg": "83.1", "colour": "4", "humidity": "0.7563", "chanceClear": "0.5133", "perfectFactor": "3.6886046391", "chanceRain": "0.572"}, {"tempAvg": "83.1", "colour": "4", "humidity": "0.7568", "chanceClear": "0.5098", "perfectFactor": "3.6658753866", "chanceRain": "0.572"}, {"tempAvg": "83.1", "colour": "4", "humidity": "0.7558", "chanceClear": "0.5112", "perfectFactor": "3.6710853039", "chanceRain": "0.572"}, {"tempAvg": "83.1", "colour": "4", "humidity": "0.7535", "chanceClear": "0.517", "perfectFactor": "3.7014385452", "chanceRain": "0.572"}, {"tempAvg": "83.1", "colour": "4", "humidity": "0.7542", "chanceClear": "0.519", "perfectFactor": "3.7192093877", "chanceRain": "0.572"}, {"tempAvg": "83.1", "colour": "4", "humidity": "0.7558", "chanceClear": "0.5197", "perfectFactor": "3.7321264328", "chanceRain": "0.572"}, {"tempAvg": "83.1", "colour": "4", "humidity": "0.7579", "chanceClear": "0.5193", "perfectFactor": "3.7483531088", "chanceRain": "0.571"}, {"tempAvg": "83.2", "colour": "4", "humidity": "0.7598", "chanceClear": "0.517", "perfectFactor": "3.7836094912", "chanceRain": "0.57"}, {"tempAvg": "83.2", "colour": "4", "humidity": "0.7604", "chanceClear": "0.5122", "perfectFactor": "3.7514413082", "chanceRain": "0.57"}, {"tempAvg": "83.2", "colour": "4", "humidity": "0.7617", "chanceClear": "0.5077", "perfectFactor": "3.7335021649", "chanceRain": "0.569"}, {"tempAvg": "83.2", "colour": "4", "humidity": "0.7637", "chanceClear": "0.5054", "perfectFactor": "3.7349930097", "chanceRain": "0.568"}, {"tempAvg": "83.3", "colour": "4", "humidity": "0.7655", "chanceClear": "0.5081", "perfectFactor": "3.7974020098", "chanceRain": "0.568"}, {"tempAvg": "83.3", "colour": "4", "humidity": "0.766", "chanceClear": "0.509", "perfectFactor": "3.8066131008", "chanceRain": "0.568"}, {"tempAvg": "83.3", "colour": "4", "humidity": "0.7667", "chanceClear": "0.5077", "perfectFactor": "3.7915635188", "chanceRain": "0.569"}, {"tempAvg": "83.3", "colour": "4", "humidity": "0.7665", "chanceClear": "0.5125", "perfectFactor": "3.8264120738", "chanceRain": "0.569"}, {"tempAvg": "83.3", "colour": "4", "humidity": "0.7677", "chanceClear": "0.5094", "perfectFactor": "3.809221181", "chanceRain": "0.569"}, {"tempAvg": "83.4", "colour": "3", "humidity": "0.7686", "chanceClear": "0.5113", "perfectFactor": "3.8528267047", "chanceRain": "0.57"}, {"tempAvg": "83.4", "colour": "3", "humidity": "0.7702", "chanceClear": "0.5132", "perfectFactor": "3.8661820592", "chanceRain": "0.571"}, {"tempAvg": "83.4", "colour": "3", "humidity": "0.7729", "chanceClear": "0.5127", "perfectFactor": "3.8578856145", "chanceRain": "0.573"}, {"tempAvg": "83.4", "colour": "3", "humidity": "0.774", "chanceClear": "0.5123", "perfectFactor": "3.8513213986", "chanceRain": "0.574"}, {"tempAvg": "83.4", "colour": "3", "humidity": "0.7734", "chanceClear": "0.5147", "perfectFactor": "3.8572884162", "chanceRain": "0.575"}, {"tempAvg": "83.4", "colour": "3", "humidity": "0.773", "chanceClear": "0.5177", "perfectFactor": "3.8686403971", "chanceRain": "0.576"}, {"tempAvg": "83.4", "colour": "3", "humidity": "0.772", "chanceClear": "0.5236", "perfectFactor": "3.9076678502", "chanceRain": "0.576"}, {"tempAvg": "83.4", "colour": "3", "humidity": "0.7725", "chanceClear": "0.531", "perfectFactor": "3.956108769", "chanceRain": "0.577"}, {"tempAvg": "83.5", "colour": "3", "humidity": "0.7721", "chanceClear": "0.5369", "perfectFactor": "4.0235299959", "chanceRain": "0.578"}]}, {"id": "8", "days": [{"tempAvg": "83.5", "colour": "3", "humidity": "0.7703", "chanceClear": "0.5416", "perfectFactor": "4.0492896229", "chanceRain": "0.578"}, {"tempAvg": "83.5", "colour": "3", "humidity": "0.7698", "chanceClear": "0.5401", "perfectFactor": "4.0258910333", "chanceRain": "0.579"}, {"tempAvg": "83.5", "colour": "3", "humidity": "0.7715", "chanceClear": "0.5373", "perfectFactor": "4.0138644569", "chanceRain": "0.579"}, {"tempAvg": "83.5", "colour": "3", "humidity": "0.7713", "chanceClear": "0.5388", "perfectFactor": "4.0240266685", "chanceRain": "0.579"}, {"tempAvg": "83.5", "colour": "3", "humidity": "0.7719", "chanceClear": "0.5372", "perfectFactor": "4.0056608088", "chanceRain": "0.58"}, {"tempAvg": "83.5", "colour": "3", "humidity": "0.7706", "chanceClear": "0.5408", "perfectFactor": "4.0257130368", "chanceRain": "0.58"}, {"tempAvg": "83.5", "colour": "3", "humidity": "0.7695", "chanceClear": "0.5399", "perfectFactor": "4.0037210429", "chanceRain": "0.581"}, {"tempAvg": "83.5", "colour": "3", "humidity": "0.7684", "chanceClear": "0.5389", "perfectFactor": "3.9905926541", "chanceRain": "0.581"}, {"tempAvg": "83.5", "colour": "3", "humidity": "0.7676", "chanceClear": "0.5394", "perfectFactor": "3.9901366313", "chanceRain": "0.581"}, {"tempAvg": "83.5", "colour": "3", "humidity": "0.7661", "chanceClear": "0.5418", "perfectFactor": "3.9905116297", "chanceRain": "0.582"}, {"tempAvg": "83.5", "colour": "3", "humidity": "0.7659", "chanceClear": "0.5383", "perfectFactor": "3.9636980876", "chanceRain": "0.582"}, {"tempAvg": "83.5", "colour": "3", "humidity": "0.7658", "chanceClear": "0.5337", "perfectFactor": "3.9293135204", "chanceRain": "0.582"}, {"tempAvg": "83.4", "colour": "3", "humidity": "0.7666", "chanceClear": "0.5259", "perfectFactor": "3.8422278402", "chanceRain": "0.582"}, {"tempAvg": "83.4", "colour": "4", "humidity": "0.7674", "chanceClear": "0.5188", "perfectFactor": "3.7852334061", "chanceRain": "0.583"}, {"tempAvg": "83.4", "colour": "4", "humidity": "0.7681", "chanceClear": "0.5123", "perfectFactor": "3.750189813", "chanceRain": "0.582"}, {"tempAvg": "83.4", "colour": "4", "humidity": "0.7686", "chanceClear": "0.5101", "perfectFactor": "3.7365158809", "chanceRain": "0.582"}, {"tempAvg": "83.4", "colour": "4", "humidity": "0.7707", "chanceClear": "0.5082", "perfectFactor": "3.7416993602", "chanceRain": "0.581"}, {"tempAvg": "83.4", "colour": "4", "humidity": "0.7717", "chanceClear": "0.5089", "perfectFactor": "3.7606688129", "chanceRain": "0.58"}, {"tempAvg": "83.3", "colour": "4", "humidity": "0.7716", "chanceClear": "0.5105", "perfectFactor": "3.7478180663", "chanceRain": "0.579"}, {"tempAvg": "83.3", "colour": "4", "humidity": "0.7707", "chanceClear": "0.5134", "perfectFactor": "3.7825966173", "chanceRain": "0.577"}, {"tempAvg": "83.3", "colour": "4", "humidity": "0.7702", "chanceClear": "0.5088", "perfectFactor": "3.7639858848", "chanceRain": "0.575"}, {"tempAvg": "83.3", "colour": "4", "humidity": "0.7701", "chanceClear": "0.5093", "perfectFactor": "3.7849235669", "chanceRain": "0.573"}, {"tempAvg": "83.3", "colour": "4", "humidity": "0.7715", "chanceClear": "0.5045", "perfectFactor": "3.7824569665", "chanceRain": "0.57"}, {"tempAvg": "83.3", "colour": "4", "humidity": "0.7723", "chanceClear": "0.5046", "perfectFactor": "3.8047442291", "chanceRain": "0.568"}, {"tempAvg": "83.3", "colour": "4", "humidity": "0.7728", "chanceClear": "0.5029", "perfectFactor": "3.8119475614", "chanceRain": "0.566"}, {"tempAvg": "83.3", "colour": "3", "humidity": "0.7722", "chanceClear": "0.507", "perfectFactor": "3.8665856315", "chanceRain": "0.563"}, {"tempAvg": "83.3", "colour": "3", "humidity": "0.7721", "chanceClear": "0.5081", "perfectFactor": "3.8922050048", "chanceRain": "0.561"}, {"tempAvg": "83.2", "colour": "3", "humidity": "0.7722", "chanceClear": "0.5144", "perfectFactor": "3.9327926077", "chanceRain": "0.558"}, {"tempAvg": "83.2", "colour": "3", "humidity": "0.7727", "chanceClear": "0.5143", "perfectFactor": "3.9523775612", "chanceRain": "0.556"}, {"tempAvg": "83.2", "colour": "3", "humidity": "0.7738", "chanceClear": "0.5113", "perfectFactor": "3.9526412182", "chanceRain": "0.554"}, {"tempAvg": "83.2", "colour": "3", "humidity": "0.7745", "chanceClear": "0.509", "perfectFactor": "3.9560815616", "chanceRain": "0.552"}]}, {"id": "9", "days": [{"tempAvg": "83.2", "colour": "3", "humidity": "0.7742", "chanceClear": "0.5086", "perfectFactor": "3.9690818496", "chanceRain": "0.55"}, {"tempAvg": "83.1", "colour": "3", "humidity": "0.7736", "chanceClear": "0.5086", "perfectFactor": "3.9480643818", "chanceRain": "0.548"}, {"tempAvg": "83.1", "colour": "3", "humidity": "0.774", "chanceClear": "0.5042", "perfectFactor": "3.933259763", "chanceRain": "0.546"}, {"tempAvg": "83.1", "colour": "3", "humidity": "0.7741", "chanceClear": "0.5022", "perfectFactor": "3.9354245721", "chanceRain": "0.544"}, {"tempAvg": "83", "colour": "3", "humidity": "0.775", "chanceClear": "0.5063", "perfectFactor": "3.962278485", "chanceRain": "0.541"}, {"tempAvg": "83", "colour": "3", "humidity": "0.7752", "chanceClear": "0.5057", "perfectFactor": "3.984477457", "chanceRain": "0.538"}, {"tempAvg": "83", "colour": "3", "humidity": "0.7753", "chanceClear": "0.5098", "perfectFactor": "4.0520818809", "chanceRain": "0.534"}, {"tempAvg": "83", "colour": "3", "humidity": "0.7741", "chanceClear": "0.5123", "perfectFactor": "4.1005485862", "chanceRain": "0.53"}, {"tempAvg": "82.9", "colour": "3", "humidity": "0.7734", "chanceClear": "0.5122", "perfectFactor": "4.0933471419", "chanceRain": "0.526"}, {"tempAvg": "82.9", "colour": "3", "humidity": "0.7743", "chanceClear": "0.5062", "perfectFactor": "4.0928271819", "chanceRain": "0.521"}, {"tempAvg": "82.9", "colour": "3", "humidity": "0.7749", "chanceClear": "0.5026", "perfectFactor": "4.1093203647", "chanceRain": "0.516"}, {"tempAvg": "82.8", "colour": "3", "humidity": "0.7746", "chanceClear": "0.4997", "perfectFactor": "4.0967236901", "chanceRain": "0.51"}, {"tempAvg": "82.8", "colour": "3", "humidity": "0.7745", "chanceClear": "0.4975", "perfectFactor": "4.119774615", "chanceRain": "0.505"}, {"tempAvg": "82.7", "colour": "3", "humidity": "0.7738", "chanceClear": "0.4988", "perfectFactor": "4.129894408", "chanceRain": "0.5"}, {"tempAvg": "82.6", "colour": "3", "humidity": "0.7734", "chanceClear": "0.5009", "perfectFactor": "4.1556750148", "chanceRain": "0.494"}, {"tempAvg": "82.6", "colour": "3", "humidity": "0.773", "chanceClear": "0.5094", "perfectFactor": "4.2740958413", "chanceRain": "0.488"}, {"tempAvg": "82.5", "colour": "3", "humidity": "0.7722", "chanceClear": "0.5147", "perfectFactor": "4.3234756765", "chanceRain": "0.482"}, {"tempAvg": "82.5", "colour": "3", "humidity": "0.7709", "chanceClear": "0.5202", "perfectFactor": "4.4128480687", "chanceRain": "0.476"}, {"tempAvg": "82.4", "colour": "3", "humidity": "0.7709", "chanceClear": "0.516", "perfectFactor": "4.3934491411", "chanceRain": "0.469"}, {"tempAvg": "82.3", "colour": "3", "humidity": "0.7715", "chanceClear": "0.5119", "perfectFactor": "4.3769396244", "chanceRain": "0.462"}, {"tempAvg": "82.2", "colour": "3", "humidity": "0.7722", "chanceClear": "0.5132", "perfectFactor": "4.4059860187", "chanceRain": "0.455"}, {"tempAvg": "82.1", "colour": "3", "humidity": "0.7717", "chanceClear": "0.512", "perfectFactor": "4.4056390042", "chanceRain": "0.448"}, {"tempAvg": "82", "colour": "3", "humidity": "0.7721", "chanceClear": "0.5071", "perfectFactor": "4.385157392", "chanceRain": "0.44"}, {"tempAvg": "81.9", "colour": "3", "humidity": "0.7711", "chanceClear": "0.5089", "perfectFactor": "4.4132312015", "chanceRain": "0.432"}, {"tempAvg": "81.8", "colour": "3", "humidity": "0.7704", "chanceClear": "0.5145", "perfectFactor": "4.4826366514", "chanceRain": "0.423"}, {"tempAvg": "81.7", "colour": "3", "humidity": "0.769", "chanceClear": "0.5212", "perfectFactor": "4.5487109772", "chanceRain": "0.415"}, {"tempAvg": "81.5", "colour": "3", "humidity": "0.7672", "chanceClear": "0.5227", "perfectFactor": "4.5258602558", "chanceRain": "0.406"}, {"tempAvg": "81.4", "colour": "3", "humidity": "0.7644", "chanceClear": "0.532", "perfectFactor": "4.6100694931", "chanceRain": "0.397"}, {"tempAvg": "81.3", "colour": "3", "humidity": "0.763", "chanceClear": "0.544", "perfectFactor": "4.7325679296", "chanceRain": "0.387"}, {"tempAvg": "81.1", "colour": "3", "humidity": "0.7601", "chanceClear": "0.5471", "perfectFactor": "4.7151648604", "chanceRain": "0.377"}]}, {"id": "10", "days": [{"tempAvg": "80.9", "colour": "3", "humidity": "0.7563", "chanceClear": "0.5479", "perfectFactor": "4.6689488183", "chanceRain": "0.367"}, {"tempAvg": "80.8", "colour": "3", "humidity": "0.7551", "chanceClear": "0.5468", "perfectFactor": "4.6725786138", "chanceRain": "0.357"}, {"tempAvg": "80.6", "colour": "3", "humidity": "0.7535", "chanceClear": "0.5492", "perfectFactor": "4.6478854215", "chanceRain": "0.347"}, {"tempAvg": "80.5", "colour": "3", "humidity": "0.7522", "chanceClear": "0.5522", "perfectFactor": "4.6815771116", "chanceRain": "0.337"}, {"tempAvg": "80.3", "colour": "3", "humidity": "0.7502", "chanceClear": "0.5598", "perfectFactor": "4.6917310247", "chanceRain": "0.327"}, {"tempAvg": "80.1", "colour": "3", "humidity": "0.7465", "chanceClear": "0.5657", "perfectFactor": "4.6725258102", "chanceRain": "0.317"}, {"tempAvg": "79.9", "colour": "3", "humidity": "0.7451", "chanceClear": "0.5711", "perfectFactor": "4.6525377431", "chanceRain": "0.308"}, {"tempAvg": "79.7", "colour": "3", "humidity": "0.7419", "chanceClear": "0.5772", "perfectFactor": "4.6228567105", "chanceRain": "0.299"}, {"tempAvg": "79.5", "colour": "3", "humidity": "0.7385", "chanceClear": "0.5809", "perfectFactor": "4.5623581028", "chanceRain": "0.291"}, {"tempAvg": "79.3", "colour": "3", "humidity": "0.7335", "chanceClear": "0.5931", "perfectFactor": "4.5540736896", "chanceRain": "0.283"}, {"tempAvg": "79.1", "colour": "3", "humidity": "0.7313", "chanceClear": "0.5988", "perfectFactor": "4.5082056198", "chanceRain": "0.275"}, {"tempAvg": "78.9", "colour": "3", "humidity": "0.7295", "chanceClear": "0.604", "perfectFactor": "4.4570273172", "chanceRain": "0.267"}, {"tempAvg": "78.7", "colour": "3", "humidity": "0.7285", "chanceClear": "0.6037", "perfectFactor": "4.3610116822", "chanceRain": "0.26"}, {"tempAvg": "78.5", "colour": "3", "humidity": "0.7278", "chanceClear": "0.6007", "perfectFactor": "4.251230309", "chanceRain": "0.252"}, {"tempAvg": "78.2", "colour": "3", "humidity": "0.7272", "chanceClear": "0.6056", "perfectFactor": "4.1229528998", "chanceRain": "0.245"}, {"tempAvg": "78", "colour": "3", "humidity": "0.7269", "chanceClear": "0.6063", "perfectFactor": "4.0299388337", "chanceRain": "0.238"}, {"tempAvg": "77.8", "colour": "3", "humidity": "0.7247", "chanceClear": "0.6079", "perfectFactor": "3.9298387777", "chanceRain": "0.231"}, {"tempAvg": "77.6", "colour": "4", "humidity": "0.7235", "chanceClear": "0.6099", "perfectFactor": "3.830159802", "chanceRain": "0.225"}, {"tempAvg": "77.3", "colour": "4", "humidity": "0.7211", "chanceClear": "0.6148", "perfectFactor": "3.6701706132", "chanceRain": "0.219"}, {"tempAvg": "77.1", "colour": "4", "humidity": "0.7189", "chanceClear": "0.621", "perfectFactor": "3.5791739147", "chanceRain": "0.214"}, {"tempAvg": "76.8", "colour": "4", "humidity": "0.7176", "chanceClear": "0.623", "perfectFactor": "3.3948312653", "chanceRain": "0.209"}, {"tempAvg": "76.6", "colour": "4", "humidity": "0.7163", "chanceClear": "0.6241", "perfectFactor": "3.2737840527", "chanceRain": "0.204"}, {"tempAvg": "76.4", "colour": "4", "humidity": "0.7156", "chanceClear": "0.6233", "perfectFactor": "3.1400756992", "chanceRain": "0.2"}, {"tempAvg": "76.1", "colour": "4", "humidity": "0.7183", "chanceClear": "0.6166", "perfectFactor": "2.9199760408", "chanceRain": "0.196"}, {"tempAvg": "75.9", "colour": "4", "humidity": "0.7223", "chanceClear": "0.5985", "perfectFactor": "2.7245057767", "chanceRain": "0.192"}, {"tempAvg": "75.7", "colour": "4", "humidity": "0.7243", "chanceClear": "0.5938", "perfectFactor": "2.5843208262", "chanceRain": "0.188"}, {"tempAvg": "75.5", "colour": "4", "humidity": "0.7254", "chanceClear": "0.5964", "perfectFactor": "2.4681459348", "chanceRain": "0.185"}, {"tempAvg": "75.3", "colour": "4", "humidity": "0.727", "chanceClear": "0.5914", "perfectFactor": "2.3212021826", "chanceRain": "0.182"}, {"tempAvg": "75.1", "colour": "4", "humidity": "0.7267", "chanceClear": "0.5884", "perfectFactor": "2.1765200433", "chanceRain": "0.179"}, {"tempAvg": "74.8", "colour": "4", "humidity": "0.7249", "chanceClear": "0.5899", "perfectFactor": "1.9732028525", "chanceRain": "0.176"}, {"tempAvg": "74.6", "colour": "5", "humidity": "0.7233", "chanceClear": "0.5942", "perfectFactor": "1.8460119307", "chanceRain": "0.174"}]}, {"id": "11", "days": [{"tempAvg": "74.4", "colour": "5", "humidity": "0.7223", "chanceClear": "0.6015", "perfectFactor": "1.7267315357", "chanceRain": "0.172"}, {"tempAvg": "74.2", "colour": "5", "humidity": "0.7227", "chanceClear": "0.6037", "perfectFactor": "1.5933456515", "chanceRain": "0.17"}, {"tempAvg": "74", "colour": "5", "humidity": "0.7227", "chanceClear": "0.6072", "perfectFactor": "1.4604044083", "chanceRain": "0.168"}, {"tempAvg": "73.8", "colour": "5", "humidity": "0.7235", "chanceClear": "0.6041", "perfectFactor": "1.3122480092", "chanceRain": "0.166"}, {"tempAvg": "73.6", "colour": "5", "humidity": "0.7223", "chanceClear": "0.6045", "perfectFactor": "1.1694707294", "chanceRain": "0.163"}, {"tempAvg": "73.4", "colour": "5", "humidity": "0.722", "chanceClear": "0.6046", "perfectFactor": "1.025475603", "chanceRain": "0.161"}, {"tempAvg": "73.2", "colour": "5", "humidity": "0.7217", "chanceClear": "0.606", "perfectFactor": "0.8837972842", "chanceRain": "0.158"}, {"tempAvg": "73", "colour": "5", "humidity": "0.7199", "chanceClear": "0.6185", "perfectFactor": "0.7515957572", "chanceRain": "0.156"}, {"tempAvg": "72.8", "colour": "5", "humidity": "0.7169", "chanceClear": "0.6275", "perfectFactor": "0.6089233896", "chanceRain": "0.154"}, {"tempAvg": "72.6", "colour": "5", "humidity": "0.7146", "chanceClear": "0.6321", "perfectFactor": "0.4596485564", "chanceRain": "0.152"}, {"tempAvg": "72.4", "colour": "5", "humidity": "0.7114", "chanceClear": "0.6369", "perfectFactor": "0.3081016488", "chanceRain": "0.15"}, {"tempAvg": "72.2", "colour": "5", "humidity": "0.71", "chanceClear": "0.6457", "perfectFactor": "0.1562387376", "chanceRain": "0.148"}, {"tempAvg": "72.1", "colour": "5", "humidity": "0.7113", "chanceClear": "0.6448", "perfectFactor": "0.0782450485", "chanceRain": "0.147"}, {"tempAvg": "71.9", "colour": "5", "humidity": "0.7119", "chanceClear": "0.6399", "perfectFactor": "0.0778070535", "chanceRain": "0.146"}, {"tempAvg": "71.7", "colour": "5", "humidity": "0.7131", "chanceClear": "0.6321", "perfectFactor": "0.2312350116", "chanceRain": "0.145"}, {"tempAvg": "71.5", "colour": "5", "humidity": "0.7144", "chanceClear": "0.625", "perfectFactor": "0.3817575", "chanceRain": "0.145"}, {"tempAvg": "71.3", "colour": "5", "humidity": "0.7163", "chanceClear": "0.6245", "perfectFactor": "0.536079493", "chanceRain": "0.144"}, {"tempAvg": "71.2", "colour": "5", "humidity": "0.7177", "chanceClear": "0.6162", "perfectFactor": "0.6064087299", "chanceRain": "0.143"}, {"tempAvg": "71", "colour": "5", "humidity": "0.7192", "chanceClear": "0.6119", "perfectFactor": "0.7542945147", "chanceRain": "0.143"}, {"tempAvg": "70.9", "colour": "5", "humidity": "0.7218", "chanceClear": "0.6039", "perfectFactor": "0.8227954398", "chanceRain": "0.142"}, {"tempAvg": "70.7", "colour": "5", "humidity": "0.7243", "chanceClear": "0.6022", "perfectFactor": "0.9730157546", "chanceRain": "0.142"}, {"tempAvg": "70.5", "colour": "5", "humidity": "0.7256", "chanceClear": "0.6019", "perfectFactor": "1.1254754753", "chanceRain": "0.141"}, {"tempAvg": "70.3", "colour": "5", "humidity": "0.7256", "chanceClear": "0.5918", "perfectFactor": "1.2555950739", "chanceRain": "0.14"}, {"tempAvg": "70.2", "colour": "5", "humidity": "0.7273", "chanceClear": "0.5897", "perfectFactor": "1.3293837555", "chanceRain": "0.139"}, {"tempAvg": "70", "colour": "5", "humidity": "0.728", "chanceClear": "0.5874", "perfectFactor": "1.4727480768", "chanceRain": "0.139"}, {"tempAvg": "69.8", "colour": "5", "humidity": "0.7272", "chanceClear": "0.5831", "perfectFactor": "1.6082621977", "chanceRain": "0.138"}, {"tempAvg": "69.7", "colour": "5", "humidity": "0.7256", "chanceClear": "0.58", "perfectFactor": "1.6687464896", "chanceRain": "0.138"}, {"tempAvg": "69.5", "colour": "5", "humidity": "0.7241", "chanceClear": "0.584", "perfectFactor": "1.820474292", "chanceRain": "0.139"}, {"tempAvg": "69.4", "colour": "4", "humidity": "0.725", "chanceClear": "0.5828", "perfectFactor": "1.891751316", "chanceRain": "0.139"}, {"tempAvg": "69.2", "colour": "4", "humidity": "0.7247", "chanceClear": "0.5813", "perfectFactor": "2.0311863192", "chanceRain": "0.139"}]}, {"id": "12", "days": [{"tempAvg": "69", "colour": "4", "humidity": "0.7252", "chanceClear": "0.5778", "perfectFactor": "2.164660213", "chanceRain": "0.139"}, {"tempAvg": "68.8", "colour": "4", "humidity": "0.725", "chanceClear": "0.5742", "perfectFactor": "2.293951968", "chanceRain": "0.139"}, {"tempAvg": "68.6", "colour": "4", "humidity": "0.7258", "chanceClear": "0.5781", "perfectFactor": "2.4565861409", "chanceRain": "0.139"}, {"tempAvg": "68.5", "colour": "4", "humidity": "0.725", "chanceClear": "0.5805", "perfectFactor": "2.53359225", "chanceRain": "0.14"}, {"tempAvg": "68.3", "colour": "4", "humidity": "0.7247", "chanceClear": "0.5847", "perfectFactor": "2.6934954033", "chanceRain": "0.141"}, {"tempAvg": "68.2", "colour": "4", "humidity": "0.7238", "chanceClear": "0.5818", "perfectFactor": "2.7459534823", "chanceRain": "0.142"}, {"tempAvg": "68", "colour": "4", "humidity": "0.7234", "chanceClear": "0.5801", "perfectFactor": "2.877081595", "chanceRain": "0.143"}, {"tempAvg": "67.8", "colour": "4", "humidity": "0.7232", "chanceClear": "0.5772", "perfectFactor": "3.00149615", "chanceRain": "0.144"}, {"tempAvg": "67.6", "colour": "4", "humidity": "0.7234", "chanceClear": "0.575", "perfectFactor": "3.125985016", "chanceRain": "0.146"}, {"tempAvg": "67.4", "colour": "4", "humidity": "0.7241", "chanceClear": "0.571", "perfectFactor": "3.2408734862", "chanceRain": "0.148"}, {"tempAvg": "67.3", "colour": "4", "humidity": "0.7263", "chanceClear": "0.5688", "perfectFactor": "3.3047076483", "chanceRain": "0.149"}, {"tempAvg": "67.1", "colour": "4", "humidity": "0.7282", "chanceClear": "0.5669", "perfectFactor": "3.4387621114", "chanceRain": "0.15"}, {"tempAvg": "67", "colour": "4", "humidity": "0.7268", "chanceClear": "0.5657", "perfectFactor": "3.4906699524", "chanceRain": "0.151"}, {"tempAvg": "66.8", "colour": "4", "humidity": "0.7256", "chanceClear": "0.5648", "perfectFactor": "3.6142746665", "chanceRain": "0.152"}, {"tempAvg": "66.6", "colour": "4", "humidity": "0.7254", "chanceClear": "0.5719", "perfectFactor": "3.794939124", "chanceRain": "0.153"}, {"tempAvg": "66.4", "colour": "3", "humidity": "0.7268", "chanceClear": "0.5704", "perfectFactor": "3.9327457326", "chanceRain": "0.153"}, {"tempAvg": "66.3", "colour": "3", "humidity": "0.7284", "chanceClear": "0.565", "perfectFactor": "3.9691142424", "chanceRain": "0.154"}, {"tempAvg": "66.1", "colour": "3", "humidity": "0.7274", "chanceClear": "0.5567", "perfectFactor": "4.0424707704", "chanceRain": "0.154"}, {"tempAvg": "66", "colour": "3", "humidity": "0.7246", "chanceClear": "0.555", "perfectFactor": "4.07783142", "chanceRain": "0.155"}, {"tempAvg": "65.8", "colour": "3", "humidity": "0.7236", "chanceClear": "0.5546", "perfectFactor": "4.1999348655", "chanceRain": "0.156"}, {"tempAvg": "65.6", "colour": "3", "humidity": "0.7246", "chanceClear": "0.5543", "perfectFactor": "4.3339186245", "chanceRain": "0.157"}, {"tempAvg": "65.5", "colour": "3", "humidity": "0.7254", "chanceClear": "0.553", "perfectFactor": "4.3909463052", "chanceRain": "0.158"}, {"tempAvg": "65.3", "colour": "3", "humidity": "0.7252", "chanceClear": "0.5541", "perfectFactor": "4.5230358499", "chanceRain": "0.16"}, {"tempAvg": "65.2", "colour": "3", "humidity": "0.7273", "chanceClear": "0.5489", "perfectFactor": "4.5552024937", "chanceRain": "0.161"}, {"tempAvg": "65.1", "colour": "3", "humidity": "0.7302", "chanceClear": "0.5433", "perfectFactor": "4.5823270036", "chanceRain": "0.163"}, {"tempAvg": "65", "colour": "3", "humidity": "0.7304", "chanceClear": "0.5398", "perfectFactor": "4.6145351437", "chanceRain": "0.164"}, {"tempAvg": "64.8", "colour": "3", "humidity": "0.7321", "chanceClear": "0.5317", "perfectFactor": "4.6804330217", "chanceRain": "0.165"}, {"tempAvg": "64.7", "colour": "3", "humidity": "0.7337", "chanceClear": "0.5258", "perfectFactor": "4.6974050167", "chanceRain": "0.166"}, {"tempAvg": "64.6", "colour": "3", "humidity": "0.7335", "chanceClear": "0.5253", "perfectFactor": "4.7502255994", "chanceRain": "0.167"}, {"tempAvg": "64.5", "colour": "3", "humidity": "0.7327", "chanceClear": "0.5213", "perfectFactor": "4.7668172448", "chanceRain": "0.168"}, {"tempAvg": "64.4", "colour": "3", "humidity": "0.733", "chanceClear": "0.521", "perfectFactor": "4.817962088", "chanceRain": "0.17"}]}], "name": "Cape Coral, FL", "slug": "cape-coral-fl"}